slack_progress_bar/__init__.py
slack_progress_bar/slack_progress_bar.py
slack_progress_bar-2.0.0.dist-info/LICENSE
slack_progress_bar-2.0.0.dist-info/METADATA
slack_progress_bar-2.0.0.dist-info/WHEEL
slack_progress_bar-2.0.0.dist-info/top_level.txt
slack_progress_bar-2.0.0.dist-info/RECORD
