Metadata-Version: 2.1
Name: slack-progress-bar
Version: 2.0.0
Summary: A Python package for displaying progress bars in Slack messages.
Home-page: https://github.com/mlizzi/slack-progress-bar
Author: Michael Lizzi
Author-email: michael.lizzi@hotmail.com
License: UNKNOWN
Platform: UNKNOWN
Classifier: Programming Language :: Python :: 3
Classifier: License :: OSI Approved :: MIT License
Classifier: Operating System :: OS Independent
Requires-Python: >=3.9
License-File: LICENSE
Requires-Dist: slack-sdk
